<?xml version="1.0" encoding="UTF-8"?>
<buildprofiles xsi:noNamespaceSchemaLocation="https://resources.jetbrains.com/writerside/1.0/build-profiles.xsd"
               xmlns:xsi="http://www.w3.org/2001/XMLSchema-instance">

    <build-profile instance="docs">
        <variables>
            <header-logo>logo.png</header-logo>
            <noindex-content>false</noindex-content>
        </variables>
    </build-profile>
    <footer>
        <copyright>PurpleMonkeyMC 2022-2024 | All rights reserved.</copyright>
        <social type="email" href="zihoupmc@163.com"/>
        <social type="bilibili" href="https://space.bilibili.com/3493143842392737"/>
        <link href="https://github.com/PurpleMonkeyMC">开发社区</link>
        <link href="https://github.com/PurpleMonkeyMC/Documentation">项目地址</link>
        <link href="https://docs.pmmc.cc/issues.html">获取帮助</link>
    </footer>
</buildprofiles>
